README.md
setup.cfg
setup.py
sakaiauthenticator/__init__.py
sakaiauthenticator/sakaiauthenticator.py
sakaiauthenticator.egg-info/PKG-INFO
sakaiauthenticator.egg-info/SOURCES.txt
sakaiauthenticator.egg-info/dependency_links.txt
sakaiauthenticator.egg-info/requires.txt
sakaiauthenticator.egg-info/top_level.txt