Metadata-Version: 1.1
Name: sakaiauthenticator
Version: 0.1.1
Summary: Allows Django authentication using Sakai
Home-page: https://gitlab.com/bubbles/sakaiauthenticator
Author: Kyle Robbertze
Author-email: krobbertze@gmail.com
License: GPL-3
Keywords: django sakai authentication backend
Platform: UNKNOWN
Classifier: Development Status :: 4 - Beta
Classifier: Environment :: Plugins
Classifier: Framework :: Django :: 2.0
Classifier: Intended Audience :: Developers
Classifier: License :: OSI Approved :: GNU General Public License v3 (GPLv3)
Classifier: Topic :: Software Development
Classifier: Programming Language :: Python :: 3
Classifier: Programming Language :: Python :: 3.4
Classifier: Programming Language :: Python :: 3.5
Classifier: Programming Language :: Python :: 3.6
